Workbook
Name AptStatus: 'Lists'!$A$5:$A$14
Name PayStages: 'Lists'!$B$5:$B$19

Sheet Units & sales
A1: Unit inventory & sales — development project
A2: One row per unit: details, list price, status and buyer. Once signed, enter the final price and log payments on the 'Buyer payments' sheet — paid and balance update here by themselves.
A4: Project | B4: Vine Towers
A5: Units | C5: =COUNTA($C$12:$C$311) -> 6 | E5: Sales value (signed) | G5: =SUMPRODUCT((($H$12:$H$311="Contract signed")+($H$12:$H$311="Handed over"))*($G$12:$G$311)) -> 8540000
A6: Sold (signed / handed over) | C6: =COUNTIF($H$12:$H$311,"Contract signed")+COUNTIF($H$12:$H$311,"Handed over") -> 3 | E6: Collected from buyers | G6: =SUM($K$12:$K$311) -> 4828000
A7: Reserved | C7: =COUNTIF($H$12:$H$311,"Reserved") -> 1 | E7: Left to collect | G7: =G5-G6 -> 3712000
A8: Available | C8: =COUNTIF($H$12:$H$311,"Available") -> 2 | E8: Unsold stock at list price | G8: =SUMPRODUCT(($H$12:$H$311<>"Contract signed")*($H$12:$H$311<>"Handed over")*($C$12:$C$311<>"")*($F$12:$F$311)) -> 6760000
A9: Sold % | C9: =IFERROR(C6/C5,0) -> 0.5 | E9: Avg price per m² (sold) | G9: =IFERROR(SUMPRODUCT((($H$12:$H$311="Contract signed")+($H$12:$H$311="Handed over"))*($G$12:$G$311))/SUMPRODUCT((($H$12:$H$311="Contract signed")+($H$12:$H$311="Handed over"))*($E$12:$E$311)),0) -> 22895.442
A11: Building | B11: Floor | C11: Unit no. | D11: Rooms | E11: Area (m²) | F11: List price | G11: Final price | H11: Status | I11: Buyer | J11: Phone | K11: Paid | L11: Balance | M11: % paid | N11: Price per m² | O11: Contract date | P11: Parking / storage | Q11: Notes
A12: Building A | B12: 1 | C12: A-1 | D12: 4 | E12: 105 | F12: 2350000 | G12: 2290000 | H12: Contract signed | I12: Cohen family | J12: 050-0000000 | K12: =IF(C12="","",SUMIF('Buyer payments'!$A$8:$A$507,C12,'Buyer payments'!$F$8:$F$507)) -> 858000 | L12: =IF(OR(C12="",AND(H12<>"Contract signed",H12<>"Handed over")),"",IF(G12="",F12,G12)-N(K12)) -> 1432000 | M12: =IF(L12="","",IFERROR(N(K12)/IF(G12="",F12,G12),0)) -> 0.37467249 | N12: =IF(OR(C12="",N(E12)=0),"",IF(G12="",F12,G12)/E12) -> 21809.524 | O12: 46109 | P12: Parking 12, storage 3
A13: Building A | B13: 1 | C13: A-2 | D13: 3 | E13: 85 | F13: 1950000 | H13: Reserved | I13: Dana Levi | J13: 052-0000000 | K13: =IF(C13="","",SUMIF('Buyer payments'!$A$8:$A$507,C13,'Buyer payments'!$F$8:$F$507)) -> 0 | L13: =IF(OR(C13="",AND(H13<>"Contract signed",H13<>"Handed over")),"",IF(G13="",F13,G13)-N(K13)) | M13: =IF(L13="","",IFERROR(N(K13)/IF(G13="",F13,G13),0)) | N13: =IF(OR(C13="",N(E13)=0),"",IF(G13="",F13,G13)/E13) -> 22941.176
A14: Building A | B14: 2 | C14: A-3 | D14: 5 | E14: 128 | F14: 2890000 | G14: 2850000 | H14: Contract signed | I14: Yossi & Michal Avraham | J14: 054-0000000 | K14: =IF(C14="","",SUMIF('Buyer payments'!$A$8:$A$507,C14,'Buyer payments'!$F$8:$F$507)) -> 570000 | L14: =IF(OR(C14="",AND(H14<>"Contract signed",H14<>"Handed over")),"",IF(G14="",F14,G14)-N(K14)) -> 2280000 | M14: =IF(L14="","",IFERROR(N(K14)/IF(G14="",F14,G14),0)) -> 0.2 | N14: =IF(OR(C14="",N(E14)=0),"",IF(G14="",F14,G14)/E14) -> 22265.625 | O14: 46189 | P14: 2 parking spaces
A15: Building A | B15: 2 | C15: A-4 | D15: 4 | E15: 104 | F15: 2390000 | H15: Available | K15: =IF(C15="","",SUMIF('Buyer payments'!$A$8:$A$507,C15,'Buyer payments'!$F$8:$F$507)) -> 0 | L15: =IF(OR(C15="",AND(H15<>"Contract signed",H15<>"Handed over")),"",IF(G15="",F15,G15)-N(K15)) | M15: =IF(L15="","",IFERROR(N(K15)/IF(G15="",F15,G15),0)) | N15: =IF(OR(C15="",N(E15)=0),"",IF(G15="",F15,G15)/E15) -> 22980.769
A16: Building A | B16: 3 | C16: A-5 | D16: 4 | E16: 104 | F16: 2420000 | H16: Available | K16: =IF(C16="","",SUMIF('Buyer payments'!$A$8:$A$507,C16,'Buyer payments'!$F$8:$F$507)) -> 0 | L16: =IF(OR(C16="",AND(H16<>"Contract signed",H16<>"Handed over")),"",IF(G16="",F16,G16)-N(K16)) | M16: =IF(L16="","",IFERROR(N(K16)/IF(G16="",F16,G16),0)) | N16: =IF(OR(C16="",N(E16)=0),"",IF(G16="",F16,G16)/E16) -> 23269.231
A17: Building A | B17: 4 | C17: A-6 | D17: 5 | E17: 140 | F17: 3450000 | G17: 3400000 | H17: Handed over | I17: Ron Golan | J17: 053-0000000 | K17: =IF(C17="","",SUMIF('Buyer payments'!$A$8:$A$507,C17,'Buyer payments'!$F$8:$F$507)) -> 3400000 | L17: =IF(OR(C17="",AND(H17<>"Contract signed",H17<>"Handed over")),"",IF(G17="",F17,G17)-N(K17)) -> 0 | M17: =IF(L17="","",IFERROR(N(K17)/IF(G17="",F17,G17),0)) -> 1 | N17: =IF(OR(C17="",N(E17)=0),"",IF(G17="",F17,G17)/E17) -> 24285.714 | O17: 45609 | P17: Parking 1
K18: =IF(C18="","",SUMIF('Buyer payments'!$A$8:$A$507,C18,'Buyer payments'!$F$8:$F$507)) | L18: =IF(OR(C18="",AND(H18<>"Contract signed",H18<>"Handed over")),"",IF(G18="",F18,G18)-N(K18)) | M18: =IF(L18="","",IFERROR(N(K18)/IF(G18="",F18,G18),0)) | N18: =IF(OR(C18="",N(E18)=0),"",IF(G18="",F18,G18)/E18)
K19: =IF(C19="","",SUMIF('Buyer payments'!$A$8:$A$507,C19,'Buyer payments'!$F$8:$F$507)) | L19: =IF(OR(C19="",AND(H19<>"Contract signed",H19<>"Handed over")),"",IF(G19="",F19,G19)-N(K19)) | M19: =IF(L19="","",IFERROR(N(K19)/IF(G19="",F19,G19),0)) | N19: =IF(OR(C19="",N(E19)=0),"",IF(G19="",F19,G19)/E19)
K20: =IF(C20="","",SUMIF('Buyer payments'!$A$8:$A$507,C20,'Buyer payments'!$F$8:$F$507)) | L20: =IF(OR(C20="",AND(H20<>"Contract signed",H20<>"Handed over")),"",IF(G20="",F20,G20)-N(K20)) | M20: =IF(L20="","",IFERROR(N(K20)/IF(G20="",F20,G20),0)) | N20: =IF(OR(C20="",N(E20)=0),"",IF(G20="",F20,G20)/E20)
K21: =IF(C21="","",SUMIF('Buyer payments'!$A$8:$A$507,C21,'Buyer payments'!$F$8:$F$507)) | L21: =IF(OR(C21="",AND(H21<>"Contract signed",H21<>"Handed over")),"",IF(G21="",F21,G21)-N(K21)) | M21: =IF(L21="","",IFERROR(N(K21)/IF(G21="",F21,G21),0)) | N21: =IF(OR(C21="",N(E21)=0),"",IF(G21="",F21,G21)/E21)
K22: =IF(C22="","",SUMIF('Buyer payments'!$A$8:$A$507,C22,'Buyer payments'!$F$8:$F$507)) | L22: =IF(OR(C22="",AND(H22<>"Contract signed",H22<>"Handed over")),"",IF(G22="",F22,G22)-N(K22)) | M22: =IF(L22="","",IFERROR(N(K22)/IF(G22="",F22,G22),0)) | N22: =IF(OR(C22="",N(E22)=0),"",IF(G22="",F22,G22)/E22)
K23: =IF(C23="","",SUMIF('Buyer payments'!$A$8:$A$507,C23,'Buyer payments'!$F$8:$F$507)) | L23: =IF(OR(C23="",AND(H23<>"Contract signed",H23<>"Handed over")),"",IF(G23="",F23,G23)-N(K23)) | M23: =IF(L23="","",IFERROR(N(K23)/IF(G23="",F23,G23),0)) | N23: =IF(OR(C23="",N(E23)=0),"",IF(G23="",F23,G23)/E23)
K24: =IF(C24="","",SUMIF('Buyer payments'!$A$8:$A$507,C24,'Buyer payments'!$F$8:$F$507)) | L24: =IF(OR(C24="",AND(H24<>"Contract signed",H24<>"Handed over")),"",IF(G24="",F24,G24)-N(K24)) | M24: =IF(L24="","",IFERROR(N(K24)/IF(G24="",F24,G24),0)) | N24: =IF(OR(C24="",N(E24)=0),"",IF(G24="",F24,G24)/E24)
K25: =IF(C25="","",SUMIF('Buyer payments'!$A$8:$A$507,C25,'Buyer payments'!$F$8:$F$507)) | L25: =IF(OR(C25="",AND(H25<>"Contract signed",H25<>"Handed over")),"",IF(G25="",F25,G25)-N(K25)) | M25: =IF(L25="","",IFERROR(N(K25)/IF(G25="",F25,G25),0)) | N25: =IF(OR(C25="",N(E25)=0),"",IF(G25="",F25,G25)/E25)
K26: =IF(C26="","",SUMIF('Buyer payments'!$A$8:$A$507,C26,'Buyer payments'!$F$8:$F$507)) | L26: =IF(OR(C26="",AND(H26<>"Contract signed",H26<>"Handed over")),"",IF(G26="",F26,G26)-N(K26)) | M26: =IF(L26="","",IFERROR(N(K26)/IF(G26="",F26,G26),0)) | N26: =IF(OR(C26="",N(E26)=0),"",IF(G26="",F26,G26)/E26)
K27: =IF(C27="","",SUMIF('Buyer payments'!$A$8:$A$507,C27,'Buyer payments'!$F$8:$F$507)) | L27: =IF(OR(C27="",AND(H27<>"Contract signed",H27<>"Handed over")),"",IF(G27="",F27,G27)-N(K27)) | M27: =IF(L27="","",IFERROR(N(K27)/IF(G27="",F27,G27),0)) | N27: =IF(OR(C27="",N(E27)=0),"",IF(G27="",F27,G27)/E27)
K28: =IF(C28="","",SUMIF('Buyer payments'!$A$8:$A$507,C28,'Buyer payments'!$F$8:$F$507)) | L28: =IF(OR(C28="",AND(H28<>"Contract signed",H28<>"Handed over")),"",IF(G28="",F28,G28)-N(K28)) | M28: =IF(L28="","",IFERROR(N(K28)/IF(G28="",F28,G28),0)) | N28: =IF(OR(C28="",N(E28)=0),"",IF(G28="",F28,G28)/E28)
K29: =IF(C29="","",SUMIF('Buyer payments'!$A$8:$A$507,C29,'Buyer payments'!$F$8:$F$507)) | L29: =IF(OR(C29="",AND(H29<>"Contract signed",H29<>"Handed over")),"",IF(G29="",F29,G29)-N(K29)) | M29: =IF(L29="","",IFERROR(N(K29)/IF(G29="",F29,G29),0)) | N29: =IF(OR(C29="",N(E29)=0),"",IF(G29="",F29,G29)/E29)
... K311: =IF(C311="","",SUMIF('Buyer payments'!$A$8:$A$507,C311,'Buyer payments'!$F$8:$F$507)) | L311: =IF(OR(C311="",AND(H311<>"Contract signed",H311<>"Handed over")),"",IF(G311="",F311,G311)-N(K311)) | M311: =IF(L311="","",IFERROR(N(K311)/IF(G311="",F311,G311),0)) | N311: =IF(OR(C311="",N(E311)=0),"",IF(G311="",F311,G311)/E311)

Sheet Buyer payments
A1: Buyer payments by stage
A2: One row per payment: unit number, stage, due date and amount per the contract, and what was actually paid. The buyer's name comes from the units sheet; an overdue unpaid payment turns red.
A4: Total due per contracts | B4: =SUM($E$8:$E$507) -> 7115000 | D4: Overdue | E4: =SUMPRODUCT(($D$8:$D$507<>"")*($D$8:$D$507<TODAY())*($E$8:$E$507-$F$8:$F$507>0)*($E$8:$E$507-$F$8:$F$507)) -> 287000
A5: Collected | B5: =SUM($F$8:$F$507) -> 4828000 | D5: Due in the next 30 days | E5: =SUMPRODUCT(($D$8:$D$507>=TODAY())*($D$8:$D$507<=TODAY()+30)*($E$8:$E$507-$F$8:$F$507>0)*($E$8:$E$507-$F$8:$F$507)) -> 855000
A7: Unit no. | B7: Buyer | C7: Stage | D7: Due date | E7: Amount due | F7: Paid | G7: Paid on | H7: Status | I7: Notes (indexation, reference...)
A8: A-1 | B8: =IF(A8="","",IFERROR(INDEX('Units & sales'!$I$12:$I$311,MATCH(A8,'Units & sales'!$C$12:$C$311,0))&"","")) -> Cohen family | C8: Deposit at signing | D8: 46109 | E8: 458000 | F8: 458000 | G8: 46109 | H8: =IF(E8="","",IF(N(F8)>=E8,"Paid",IF(AND(D8<>"",D8<TODAY()),"Overdue",IF(N(F8)>0,"Part paid","Upcoming")))) -> Paid
A9: A-1 | B9: =IF(A9="","",IFERROR(INDEX('Units & sales'!$I$12:$I$311,MATCH(A9,'Units & sales'!$C$12:$C$311,0))&"","")) -> Cohen family | C9: Frame done | D9: 46289 | E9: 687000 | F9: 400000 | G9: 46294 | H9: =IF(E9="","",IF(N(F9)>=E9,"Paid",IF(AND(D9<>"",D9<TODAY()),"Overdue",IF(N(F9)>0,"Part paid","Upcoming")))) -> Overdue
A10: A-1 | B10: =IF(A10="","",IFERROR(INDEX('Units & sales'!$I$12:$I$311,MATCH(A10,'Units & sales'!$C$12:$C$311,0))&"","")) -> Cohen family | C10: Key handover | D10: 46609 | E10: 1145000 | H10: =IF(E10="","",IF(N(F10)>=E10,"Paid",IF(AND(D10<>"",D10<TODAY()),"Overdue",IF(N(F10)>0,"Part paid","Upcoming")))) -> Upcoming
A11: A-3 | B11: =IF(A11="","",IFERROR(INDEX('Units & sales'!$I$12:$I$311,MATCH(A11,'Units & sales'!$C$12:$C$311,0))&"","")) -> Yossi & Michal Avraham | C11: Deposit at signing | D11: 46189 | E11: 570000 | F11: 570000 | G11: 46191 | H11: =IF(E11="","",IF(N(F11)>=E11,"Paid",IF(AND(D11<>"",D11<TODAY()),"Overdue",IF(N(F11)>0,"Part paid","Upcoming")))) -> Paid
A12: A-3 | B12: =IF(A12="","",IFERROR(INDEX('Units & sales'!$I$12:$I$311,MATCH(A12,'Units & sales'!$C$12:$C$311,0))&"","")) -> Yossi & Michal Avraham | C12: Frame done | D12: 46329 | E12: 855000 | H12: =IF(E12="","",IF(N(F12)>=E12,"Paid",IF(AND(D12<>"",D12<TODAY()),"Overdue",IF(N(F12)>0,"Part paid","Upcoming")))) -> Upcoming
A13: A-6 | B13: =IF(A13="","",IFERROR(INDEX('Units & sales'!$I$12:$I$311,MATCH(A13,'Units & sales'!$C$12:$C$311,0))&"","")) -> Ron Golan | C13: Deposit at signing | D13: 45609 | E13: 3400000 | F13: 3400000 | G13: 45619 | H13: =IF(E13="","",IF(N(F13)>=E13,"Paid",IF(AND(D13<>"",D13<TODAY()),"Overdue",IF(N(F13)>0,"Part paid","Upcoming")))) -> Paid
B14: =IF(A14="","",IFERROR(INDEX('Units & sales'!$I$12:$I$311,MATCH(A14,'Units & sales'!$C$12:$C$311,0))&"","")) | H14: =IF(E14="","",IF(N(F14)>=E14,"Paid",IF(AND(D14<>"",D14<TODAY()),"Overdue",IF(N(F14)>0,"Part paid","Upcoming"))))
B15: =IF(A15="","",IFERROR(INDEX('Units & sales'!$I$12:$I$311,MATCH(A15,'Units & sales'!$C$12:$C$311,0))&"","")) | H15: =IF(E15="","",IF(N(F15)>=E15,"Paid",IF(AND(D15<>"",D15<TODAY()),"Overdue",IF(N(F15)>0,"Part paid","Upcoming"))))
B16: =IF(A16="","",IFERROR(INDEX('Units & sales'!$I$12:$I$311,MATCH(A16,'Units & sales'!$C$12:$C$311,0))&"","")) | H16: =IF(E16="","",IF(N(F16)>=E16,"Paid",IF(AND(D16<>"",D16<TODAY()),"Overdue",IF(N(F16)>0,"Part paid","Upcoming"))))
B17: =IF(A17="","",IFERROR(INDEX('Units & sales'!$I$12:$I$311,MATCH(A17,'Units & sales'!$C$12:$C$311,0))&"","")) | H17: =IF(E17="","",IF(N(F17)>=E17,"Paid",IF(AND(D17<>"",D17<TODAY()),"Overdue",IF(N(F17)>0,"Part paid","Upcoming"))))
B18: =IF(A18="","",IFERROR(INDEX('Units & sales'!$I$12:$I$311,MATCH(A18,'Units & sales'!$C$12:$C$311,0))&"","")) | H18: =IF(E18="","",IF(N(F18)>=E18,"Paid",IF(AND(D18<>"",D18<TODAY()),"Overdue",IF(N(F18)>0,"Part paid","Upcoming"))))
B19: =IF(A19="","",IFERROR(INDEX('Units & sales'!$I$12:$I$311,MATCH(A19,'Units & sales'!$C$12:$C$311,0))&"","")) | H19: =IF(E19="","",IF(N(F19)>=E19,"Paid",IF(AND(D19<>"",D19<TODAY()),"Overdue",IF(N(F19)>0,"Part paid","Upcoming"))))
B20: =IF(A20="","",IFERROR(INDEX('Units & sales'!$I$12:$I$311,MATCH(A20,'Units & sales'!$C$12:$C$311,0))&"","")) | H20: =IF(E20="","",IF(N(F20)>=E20,"Paid",IF(AND(D20<>"",D20<TODAY()),"Overdue",IF(N(F20)>0,"Part paid","Upcoming"))))
B21: =IF(A21="","",IFERROR(INDEX('Units & sales'!$I$12:$I$311,MATCH(A21,'Units & sales'!$C$12:$C$311,0))&"","")) | H21: =IF(E21="","",IF(N(F21)>=E21,"Paid",IF(AND(D21<>"",D21<TODAY()),"Overdue",IF(N(F21)>0,"Part paid","Upcoming"))))
B22: =IF(A22="","",IFERROR(INDEX('Units & sales'!$I$12:$I$311,MATCH(A22,'Units & sales'!$C$12:$C$311,0))&"","")) | H22: =IF(E22="","",IF(N(F22)>=E22,"Paid",IF(AND(D22<>"",D22<TODAY()),"Overdue",IF(N(F22)>0,"Part paid","Upcoming"))))
B23: =IF(A23="","",IFERROR(INDEX('Units & sales'!$I$12:$I$311,MATCH(A23,'Units & sales'!$C$12:$C$311,0))&"","")) | H23: =IF(E23="","",IF(N(F23)>=E23,"Paid",IF(AND(D23<>"",D23<TODAY()),"Overdue",IF(N(F23)>0,"Part paid","Upcoming"))))
B24: =IF(A24="","",IFERROR(INDEX('Units & sales'!$I$12:$I$311,MATCH(A24,'Units & sales'!$C$12:$C$311,0))&"","")) | H24: =IF(E24="","",IF(N(F24)>=E24,"Paid",IF(AND(D24<>"",D24<TODAY()),"Overdue",IF(N(F24)>0,"Part paid","Upcoming"))))
B25: =IF(A25="","",IFERROR(INDEX('Units & sales'!$I$12:$I$311,MATCH(A25,'Units & sales'!$C$12:$C$311,0))&"","")) | H25: =IF(E25="","",IF(N(F25)>=E25,"Paid",IF(AND(D25<>"",D25<TODAY()),"Overdue",IF(N(F25)>0,"Part paid","Upcoming"))))
... B507: =IF(A507="","",IFERROR(INDEX('Units & sales'!$I$12:$I$311,MATCH(A507,'Units & sales'!$C$12:$C$311,0))&"","")) | H507: =IF(E507="","",IF(N(F507)>=E507,"Paid",IF(AND(D507<>"",D507<TODAY()),"Overdue",IF(N(F507)>0,"Part paid","Upcoming"))))

Sheet Lists
A1: Dropdown lists
A2: Change, add or remove items — the dropdowns in the workbook update by themselves.
A4: Unit status | B4: Payment stages
A5: Available | B5: Deposit at signing
A6: Reserved | B6: Foundations done
A7: Contract signed | B7: Frame done
A8: Handed over | B8: Plaster & windows
B9: Finishing
B10: Key handover
B11: Other
