Workbook
Name BuildCats: 'Lists'!$A$5:$A$39

Sheet Construction budget
A1: Building construction budget — plan vs actual
A2: One row per line item: planned budget, signed contract and what was paid. See overruns per item, what's left to pay, cost per m² and per unit, and how much contingency is left.
A4: Project | B4: Residential building, 12 Vine St | D4: Original plan (total) | E4: =SUM($D$10:$D$209) -> 19560000 | G4: Paid so far | H4: =SUM($F$10:$F$209) -> 13260000 | J4: Contingency left | K4: =E5-E6 -> 1079200
A5: Housing units | B5: 24 | D5: Incl. contingency | E5: =E4*(1+B7) -> 20929200 | G5: Left to pay | H5: =E6-H4 -> 6590000 | J5: Paid vs forecast | K5: =IFERROR(H4/E6,0) -> 0.66801008
A6: Total built area (m²) | B6: 3200 | D6: Actual cost forecast | E6: =SUM($E$10:$E$209)+SUMIF($E$10:$E$209,"",$D$10:$D$209) -> 19850000 | G6: Cost per m² | H6: =IFERROR(E6/B6,0) -> 6203.125
A7: Contingency reserve | B7: 0.07 | D7: Left vs plan | E7: =E4-E6 -> -290000 | G7: Cost per unit | H7: =IFERROR(E6/B5,0) -> 827083.33
A9: Category | B9: Item | C9: Supplier / contractor | D9: Original plan | E9: Actual agreed price | F9: Paid | G9: Left to pay | H9: Variance | I9: Variance % | J9: Next payment | K9: Status | L9: Notes
A10: Land & taxes | B10: Land purchase | C10: Land owners | D10: 9500000 | E10: 9500000 | F10: 9500000 | G10: =IF(AND(D10="",E10=""),"",IF(E10="",D10,E10)-N(F10)) -> 0 | H10: =IF(OR(D10="",E10=""),"",E10-D10) -> 0 | I10: =IF(H10="","",IFERROR(H10/D10,0)) -> 0 | K10: =IF(AND(D10="",E10=""),"",IF(N(G10)<=0,"Fully paid",IF(N(H10)>0,"Over budget","On budget"))) -> Fully paid | M10: =IF(AND(D10="",E10=""),"",IF(E10="",D10,E10)) -> 9500000
A11: Design & permits | B11: Architect | C11: Architects office | D11: 420000 | E11: 450000 | F11: 300000 | G11: =IF(AND(D11="",E11=""),"",IF(E11="",D11,E11)-N(F11)) -> 150000 | H11: =IF(OR(D11="",E11=""),"",E11-D11) -> 30000 | I11: =IF(H11="","",IFERROR(H11/D11,0)) -> 0.071428571 | J11: 46323 | K11: =IF(AND(D11="",E11=""),"",IF(N(G11)<=0,"Fully paid",IF(N(H11)>0,"Over budget","On budget"))) -> Over budget | M11: =IF(AND(D11="",E11=""),"",IF(E11="",D11,E11)) -> 450000
A12: Fees & levies | B12: Betterment levy & permit fees | C12: Local committee | D12: 1300000 | E12: 1240000 | F12: 1240000 | G12: =IF(AND(D12="",E12=""),"",IF(E12="",D12,E12)-N(F12)) -> 0 | H12: =IF(OR(D12="",E12=""),"",E12-D12) -> -60000 | I12: =IF(H12="","",IFERROR(H12/D12,0)) -> -0.046153846 | K12: =IF(AND(D12="",E12=""),"",IF(N(G12)<=0,"Fully paid",IF(N(H12)>0,"Over budget","On budget"))) -> Fully paid | M12: =IF(AND(D12="",E12=""),"",IF(E12="",D12,E12)) -> 1240000
A13: Structure | B13: Frame floors 1-8 | C13: Frame contractor | D13: 6800000 | E13: 7150000 | F13: 2100000 | G13: =IF(AND(D13="",E13=""),"",IF(E13="",D13,E13)-N(F13)) -> 5050000 | H13: =IF(OR(D13="",E13=""),"",E13-D13) -> 350000 | I13: =IF(H13="","",IFERROR(H13/D13,0)) -> 0.051470588 | J13: 46314 | K13: =IF(AND(D13="",E13=""),"",IF(N(G13)<=0,"Fully paid",IF(N(H13)>0,"Over budget","On budget"))) -> Over budget | M13: =IF(AND(D13="",E13=""),"",IF(E13="",D13,E13)) -> 7150000
A14: Plumbing | B14: Plumbing | C14: Plumbing contractor | D14: 900000 | F14: 0 | G14: =IF(AND(D14="",E14=""),"",IF(E14="",D14,E14)-N(F14)) -> 900000 | H14: =IF(OR(D14="",E14=""),"",E14-D14) | I14: =IF(H14="","",IFERROR(H14/D14,0)) | J14: 46399 | K14: =IF(AND(D14="",E14=""),"",IF(N(G14)<=0,"Fully paid",IF(N(H14)>0,"Over budget","On budget"))) -> On budget | M14: =IF(AND(D14="",E14=""),"",IF(E14="",D14,E14)) -> 900000
A15: Lifts | B15: 2 lifts | C15: Lift company | D15: 640000 | E15: 610000 | F15: 120000 | G15: =IF(AND(D15="",E15=""),"",IF(E15="",D15,E15)-N(F15)) -> 490000 | H15: =IF(OR(D15="",E15=""),"",E15-D15) -> -30000 | I15: =IF(H15="","",IFERROR(H15/D15,0)) -> -0.046875 | J15: 46369 | K15: =IF(AND(D15="",E15=""),"",IF(N(G15)<=0,"Fully paid",IF(N(H15)>0,"Over budget","On budget"))) -> On budget | M15: =IF(AND(D15="",E15=""),"",IF(E15="",D15,E15)) -> 610000
G16: =IF(AND(D16="",E16=""),"",IF(E16="",D16,E16)-N(F16)) | H16: =IF(OR(D16="",E16=""),"",E16-D16) | I16: =IF(H16="","",IFERROR(H16/D16,0)) | K16: =IF(AND(D16="",E16=""),"",IF(N(G16)<=0,"Fully paid",IF(N(H16)>0,"Over budget","On budget"))) | M16: =IF(AND(D16="",E16=""),"",IF(E16="",D16,E16))
G17: =IF(AND(D17="",E17=""),"",IF(E17="",D17,E17)-N(F17)) | H17: =IF(OR(D17="",E17=""),"",E17-D17) | I17: =IF(H17="","",IFERROR(H17/D17,0)) | K17: =IF(AND(D17="",E17=""),"",IF(N(G17)<=0,"Fully paid",IF(N(H17)>0,"Over budget","On budget"))) | M17: =IF(AND(D17="",E17=""),"",IF(E17="",D17,E17))
G18: =IF(AND(D18="",E18=""),"",IF(E18="",D18,E18)-N(F18)) | H18: =IF(OR(D18="",E18=""),"",E18-D18) | I18: =IF(H18="","",IFERROR(H18/D18,0)) | K18: =IF(AND(D18="",E18=""),"",IF(N(G18)<=0,"Fully paid",IF(N(H18)>0,"Over budget","On budget"))) | M18: =IF(AND(D18="",E18=""),"",IF(E18="",D18,E18))
G19: =IF(AND(D19="",E19=""),"",IF(E19="",D19,E19)-N(F19)) | H19: =IF(OR(D19="",E19=""),"",E19-D19) | I19: =IF(H19="","",IFERROR(H19/D19,0)) | K19: =IF(AND(D19="",E19=""),"",IF(N(G19)<=0,"Fully paid",IF(N(H19)>0,"Over budget","On budget"))) | M19: =IF(AND(D19="",E19=""),"",IF(E19="",D19,E19))
G20: =IF(AND(D20="",E20=""),"",IF(E20="",D20,E20)-N(F20)) | H20: =IF(OR(D20="",E20=""),"",E20-D20) | I20: =IF(H20="","",IFERROR(H20/D20,0)) | K20: =IF(AND(D20="",E20=""),"",IF(N(G20)<=0,"Fully paid",IF(N(H20)>0,"Over budget","On budget"))) | M20: =IF(AND(D20="",E20=""),"",IF(E20="",D20,E20))
G21: =IF(AND(D21="",E21=""),"",IF(E21="",D21,E21)-N(F21)) | H21: =IF(OR(D21="",E21=""),"",E21-D21) | I21: =IF(H21="","",IFERROR(H21/D21,0)) | K21: =IF(AND(D21="",E21=""),"",IF(N(G21)<=0,"Fully paid",IF(N(H21)>0,"Over budget","On budget"))) | M21: =IF(AND(D21="",E21=""),"",IF(E21="",D21,E21))
G22: =IF(AND(D22="",E22=""),"",IF(E22="",D22,E22)-N(F22)) | H22: =IF(OR(D22="",E22=""),"",E22-D22) | I22: =IF(H22="","",IFERROR(H22/D22,0)) | K22: =IF(AND(D22="",E22=""),"",IF(N(G22)<=0,"Fully paid",IF(N(H22)>0,"Over budget","On budget"))) | M22: =IF(AND(D22="",E22=""),"",IF(E22="",D22,E22))
G23: =IF(AND(D23="",E23=""),"",IF(E23="",D23,E23)-N(F23)) | H23: =IF(OR(D23="",E23=""),"",E23-D23) | I23: =IF(H23="","",IFERROR(H23/D23,0)) | K23: =IF(AND(D23="",E23=""),"",IF(N(G23)<=0,"Fully paid",IF(N(H23)>0,"Over budget","On budget"))) | M23: =IF(AND(D23="",E23=""),"",IF(E23="",D23,E23))
G24: =IF(AND(D24="",E24=""),"",IF(E24="",D24,E24)-N(F24)) | H24: =IF(OR(D24="",E24=""),"",E24-D24) | I24: =IF(H24="","",IFERROR(H24/D24,0)) | K24: =IF(AND(D24="",E24=""),"",IF(N(G24)<=0,"Fully paid",IF(N(H24)>0,"Over budget","On budget"))) | M24: =IF(AND(D24="",E24=""),"",IF(E24="",D24,E24))
G25: =IF(AND(D25="",E25=""),"",IF(E25="",D25,E25)-N(F25)) | H25: =IF(OR(D25="",E25=""),"",E25-D25) | I25: =IF(H25="","",IFERROR(H25/D25,0)) | K25: =IF(AND(D25="",E25=""),"",IF(N(G25)<=0,"Fully paid",IF(N(H25)>0,"Over budget","On budget"))) | M25: =IF(AND(D25="",E25=""),"",IF(E25="",D25,E25))
G26: =IF(AND(D26="",E26=""),"",IF(E26="",D26,E26)-N(F26)) | H26: =IF(OR(D26="",E26=""),"",E26-D26) | I26: =IF(H26="","",IFERROR(H26/D26,0)) | K26: =IF(AND(D26="",E26=""),"",IF(N(G26)<=0,"Fully paid",IF(N(H26)>0,"Over budget","On budget"))) | M26: =IF(AND(D26="",E26=""),"",IF(E26="",D26,E26))
G27: =IF(AND(D27="",E27=""),"",IF(E27="",D27,E27)-N(F27)) | H27: =IF(OR(D27="",E27=""),"",E27-D27) | I27: =IF(H27="","",IFERROR(H27/D27,0)) | K27: =IF(AND(D27="",E27=""),"",IF(N(G27)<=0,"Fully paid",IF(N(H27)>0,"Over budget","On budget"))) | M27: =IF(AND(D27="",E27=""),"",IF(E27="",D27,E27))
... G209: =IF(AND(D209="",E209=""),"",IF(E209="",D209,E209)-N(F209)) | H209: =IF(OR(D209="",E209=""),"",E209-D209) | I209: =IF(H209="","",IFERROR(H209/D209,0)) | K209: =IF(AND(D209="",E209=""),"",IF(N(G209)<=0,"Fully paid",IF(N(H209)>0,"Over budget","On budget"))) | M209: =IF(AND(D209="",E209=""),"",IF(E209="",D209,E209))

Sheet By category
A1: Summary by category
A2: Updates by itself from the budget sheet. Categories come from the Lists sheet.
A4: Category | B4: Original plan | C4: Actual forecast | D4: Difference | E4: Paid
A5: =IF('Lists'!A5="","",'Lists'!A5) -> Land & taxes | B5: =IF(A5="","",SUMIF('Construction budget'!$A$10:$A$209,A5,'Construction budget'!$D$10:$D$209)) -> 9500000 | C5: =IF(A5="","",SUMIF('Construction budget'!$A$10:$A$209,A5,'Construction budget'!$M$10:$M$209)) -> 9500000 | D5: =IF(A5="","",C5-B5) -> 0 | E5: =IF(A5="","",SUMIF('Construction budget'!$A$10:$A$209,A5,'Construction budget'!$F$10:$F$209)) -> 9500000
A6: =IF('Lists'!A6="","",'Lists'!A6) -> Design & permits | B6: =IF(A6="","",SUMIF('Construction budget'!$A$10:$A$209,A6,'Construction budget'!$D$10:$D$209)) -> 420000 | C6: =IF(A6="","",SUMIF('Construction budget'!$A$10:$A$209,A6,'Construction budget'!$M$10:$M$209)) -> 450000 | D6: =IF(A6="","",C6-B6) -> 30000 | E6: =IF(A6="","",SUMIF('Construction budget'!$A$10:$A$209,A6,'Construction budget'!$F$10:$F$209)) -> 300000
A7: =IF('Lists'!A7="","",'Lists'!A7) -> Fees & levies | B7: =IF(A7="","",SUMIF('Construction budget'!$A$10:$A$209,A7,'Construction budget'!$D$10:$D$209)) -> 1300000 | C7: =IF(A7="","",SUMIF('Construction budget'!$A$10:$A$209,A7,'Construction budget'!$M$10:$M$209)) -> 1240000 | D7: =IF(A7="","",C7-B7) -> -60000 | E7: =IF(A7="","",SUMIF('Construction budget'!$A$10:$A$209,A7,'Construction budget'!$F$10:$F$209)) -> 1240000
A8: =IF('Lists'!A8="","",'Lists'!A8) -> Earthworks & foundations | B8: =IF(A8="","",SUMIF('Construction budget'!$A$10:$A$209,A8,'Construction budget'!$D$10:$D$209)) -> 0 | C8: =IF(A8="","",SUMIF('Construction budget'!$A$10:$A$209,A8,'Construction budget'!$M$10:$M$209)) -> 0 | D8: =IF(A8="","",C8-B8) -> 0 | E8: =IF(A8="","",SUMIF('Construction budget'!$A$10:$A$209,A8,'Construction budget'!$F$10:$F$209)) -> 0
A9: =IF('Lists'!A9="","",'Lists'!A9) -> Structure | B9: =IF(A9="","",SUMIF('Construction budget'!$A$10:$A$209,A9,'Construction budget'!$D$10:$D$209)) -> 6800000 | C9: =IF(A9="","",SUMIF('Construction budget'!$A$10:$A$209,A9,'Construction budget'!$M$10:$M$209)) -> 7150000 | D9: =IF(A9="","",C9-B9) -> 350000 | E9: =IF(A9="","",SUMIF('Construction budget'!$A$10:$A$209,A9,'Construction budget'!$F$10:$F$209)) -> 2100000
A10: =IF('Lists'!A10="","",'Lists'!A10) -> Plumbing | B10: =IF(A10="","",SUMIF('Construction budget'!$A$10:$A$209,A10,'Construction budget'!$D$10:$D$209)) -> 900000 | C10: =IF(A10="","",SUMIF('Construction budget'!$A$10:$A$209,A10,'Construction budget'!$M$10:$M$209)) -> 900000 | D10: =IF(A10="","",C10-B10) -> 0 | E10: =IF(A10="","",SUMIF('Construction budget'!$A$10:$A$209,A10,'Construction budget'!$F$10:$F$209)) -> 0
A11: =IF('Lists'!A11="","",'Lists'!A11) -> Electrical | B11: =IF(A11="","",SUMIF('Construction budget'!$A$10:$A$209,A11,'Construction budget'!$D$10:$D$209)) -> 0 | C11: =IF(A11="","",SUMIF('Construction budget'!$A$10:$A$209,A11,'Construction budget'!$M$10:$M$209)) -> 0 | D11: =IF(A11="","",C11-B11) -> 0 | E11: =IF(A11="","",SUMIF('Construction budget'!$A$10:$A$209,A11,'Construction budget'!$F$10:$F$209)) -> 0
A12: =IF('Lists'!A12="","",'Lists'!A12) -> Waterproofing | B12: =IF(A12="","",SUMIF('Construction budget'!$A$10:$A$209,A12,'Construction budget'!$D$10:$D$209)) -> 0 | C12: =IF(A12="","",SUMIF('Construction budget'!$A$10:$A$209,A12,'Construction budget'!$M$10:$M$209)) -> 0 | D12: =IF(A12="","",C12-B12) -> 0 | E12: =IF(A12="","",SUMIF('Construction budget'!$A$10:$A$209,A12,'Construction budget'!$F$10:$F$209)) -> 0
A13: =IF('Lists'!A13="","",'Lists'!A13) -> Aluminium & windows | B13: =IF(A13="","",SUMIF('Construction budget'!$A$10:$A$209,A13,'Construction budget'!$D$10:$D$209)) -> 0 | C13: =IF(A13="","",SUMIF('Construction budget'!$A$10:$A$209,A13,'Construction budget'!$M$10:$M$209)) -> 0 | D13: =IF(A13="","",C13-B13) -> 0 | E13: =IF(A13="","",SUMIF('Construction budget'!$A$10:$A$209,A13,'Construction budget'!$F$10:$F$209)) -> 0
A14: =IF('Lists'!A14="","",'Lists'!A14) -> Plaster & paint | B14: =IF(A14="","",SUMIF('Construction budget'!$A$10:$A$209,A14,'Construction budget'!$D$10:$D$209)) -> 0 | C14: =IF(A14="","",SUMIF('Construction budget'!$A$10:$A$209,A14,'Construction budget'!$M$10:$M$209)) -> 0 | D14: =IF(A14="","",C14-B14) -> 0 | E14: =IF(A14="","",SUMIF('Construction budget'!$A$10:$A$209,A14,'Construction budget'!$F$10:$F$209)) -> 0
A15: =IF('Lists'!A15="","",'Lists'!A15) -> Flooring & cladding | B15: =IF(A15="","",SUMIF('Construction budget'!$A$10:$A$209,A15,'Construction budget'!$D$10:$D$209)) -> 0 | C15: =IF(A15="","",SUMIF('Construction budget'!$A$10:$A$209,A15,'Construction budget'!$M$10:$M$209)) -> 0 | D15: =IF(A15="","",C15-B15) -> 0 | E15: =IF(A15="","",SUMIF('Construction budget'!$A$10:$A$209,A15,'Construction budget'!$F$10:$F$209)) -> 0
A16: =IF('Lists'!A16="","",'Lists'!A16) -> Kitchens & carpentry | B16: =IF(A16="","",SUMIF('Construction budget'!$A$10:$A$209,A16,'Construction budget'!$D$10:$D$209)) -> 0 | C16: =IF(A16="","",SUMIF('Construction budget'!$A$10:$A$209,A16,'Construction budget'!$M$10:$M$209)) -> 0 | D16: =IF(A16="","",C16-B16) -> 0 | E16: =IF(A16="","",SUMIF('Construction budget'!$A$10:$A$209,A16,'Construction budget'!$F$10:$F$209)) -> 0
... A39: =IF('Lists'!A39="","",'Lists'!A39) | B39: =IF(A39="","",SUMIF('Construction budget'!$A$10:$A$209,A39,'Construction budget'!$D$10:$D$209)) | C39: =IF(A39="","",SUMIF('Construction budget'!$A$10:$A$209,A39,'Construction budget'!$M$10:$M$209)) | D39: =IF(A39="","",C39-B39) | E39: =IF(A39="","",SUMIF('Construction budget'!$A$10:$A$209,A39,'Construction budget'!$F$10:$F$209))
A41: Total | B41: =SUM(B5:B39) -> 19560000 | C41: =SUM(C5:C39) -> 19850000 | D41: =SUM(D5:D39) -> 290000 | E41: =SUM(E5:E39) -> 13260000

Sheet Lists
A1: Dropdown lists
A2: Change, add or remove items — the dropdowns in the workbook update by themselves.
A4: Categories
A5: Land & taxes
A6: Design & permits
A7: Fees & levies
A8: Earthworks & foundations
A9: Structure
A10: Plumbing
A11: Electrical
A12: Waterproofing
A13: Aluminium & windows
... A26: Other
